{
  "ranges": [
    {
      "min": "0x80000000000000000",
      "max": "0x82aaaaaaaaaaaaaaa",
      "status": "1MVDYgVaSN6iKKEsbzRUAYFrYJadLYZvvZ"
    },
    {
      "min": "0x82aaaaaaaaaaaaaaa",
      "max": "0x85555555555555554",
      "status": "1MVDYgVaSN6iKKEsbzRUAYFrYJadLYZvvZ"
    },
    {
      "min": "0x85555555555555554",
      "max": "0x87ffffffffffffffe",
      "status": "1MVDYgVaSN6iKKEsbzRUAYFrYJadLYZvvZ"
    },
    {
      "min": "0x87ffffffffffffffe",
      "max": "0x8aaaaaaaaaaaaaaa8",
      "status": "1MVDYgVaSN6iKKEsbzRUAYFrYJadLYZvvZ"
    },
    {
      "min": "0x8aaaaaaaaaaaaaaa8",
      "max": "0x8d555555555555552",
      "status": "1MVDYgVaSN6iKKEsbzRUAYFrYJadLYZvvZ"
    },
    {
      "min": "0x8d555555555555552",
      "max": "0x8fffffffffffffffc",
      "status": "1MVDYgVaSN6iKKEsbzRUAYFrYJadLYZvvZ"
    },
    {
      "min": "0x8fffffffffffffffc",
      "max": "0x92aaaaaaaaaaaaaa6",
      "status": "1MVDYgVaSN6iKKEsbzRUAYFrYJadLYZvvZ"
    },
    {
      "min": "0x92aaaaaaaaaaaaaa6",
      "max": "0x95555555555555550",
      "status": "1MVDYgVaSN6iKKEsbzRUAYFrYJadLYZvvZ"
    },
    {
      "min": "0x95555555555555550",
      "max": "0x97ffffffffffffffa",
      "status": "1MVDYgVaSN6iKKEsbzRUAYFrYJadLYZvvZ"
    },
    {
      "min": "0x97ffffffffffffffa",
      "max": "0x9aaaaaaaaaaaaaaa4",
      "status": "1MVDYgVaSN6iKKEsbzRUAYFrYJadLYZvvZ"
    },
    {
      "min": "0x9aaaaaaaaaaaaaaa4",
      "max": "0x9d55555555555554e",
      "status": "1MVDYgVaSN6iKKEsbzRUAYFrYJadLYZvvZ"
    },
    {
      "min": "0x9d55555555555554e",
      "max": "0x9fffffffffffffff8",
      "status": "1MVDYgVaSN6iKKEsbzRUAYFrYJadLYZvvZ"
    },
    {
      "min": "0x9fffffffffffffff8",
      "max": "0xa2aaaaaaaaaaaaaa2",
      "status": "1MVDYgVaSN6iKKEsbzRUAYFrYJadLYZvvZ"
    },
    {
      "min": "0xa2aaaaaaaaaaaaaa2",
      "max": "0xa555555555555554c",
      "status": "1MVDYgVaSN6iKKEsbzRUAYFrYJadLYZvvZ"
    },
    {
      "min": "0xa555555555555554c",
      "max": "0xa7ffffffffffffff6",
      "status": "1MVDYgVaSN6iKKEsbzRUAYFrYJadLYZvvZ"
    },
    {
      "min": "0xa7ffffffffffffff6",
      "max": "0xaaaaaaaaaaaaaaaa0",
      "status": "1MVDYgVaSN6iKKEsbzRUAYFrYJadLYZvvZ"
    },
    {
      "min": "0xaaaaaaaaaaaaaaaa0",
      "max": "0xad55555555555554a",
      "status": "1MVDYgVaSN6iKKEsbzRUAYFrYJadLYZvvZ"
    },
    {
      "min": "0xad55555555555554a",
      "max": "0xafffffffffffffff4",
      "status": "1MVDYgVaSN6iKKEsbzRUAYFrYJadLYZvvZ"
    },
    {
      "min": "0xafffffffffffffff4",
      "max": "0xb2aaaaaaaaaaaaa9e",
      "status": "1MVDYgVaSN6iKKEsbzRUAYFrYJadLYZvvZ"
    },
    {
      "min": "0xb2aaaaaaaaaaaaa9e",
      "max": "0xb5555555555555548",
      "status": "1MVDYgVaSN6iKKEsbzRUAYFrYJadLYZvvZ"
    },
    {
      "min": "0xb5555555555555548",
      "max": "0xb7ffffffffffffff2",
      "status": "1MVDYgVaSN6iKKEsbzRUAYFrYJadLYZvvZ"
    },
    {
      "min": "0xb7ffffffffffffff2",
      "max": "0xbaaaaaaaaaaaaaa9c",
      "status": "1MVDYgVaSN6iKKEsbzRUAYFrYJadLYZvvZ"
    },
    {
      "min": "0xbaaaaaaaaaaaaaa9c",
      "max": "0xbd555555555555546",
      "status": "1MVDYgVaSN6iKKEsbzRUAYFrYJadLYZvvZ"
    },
    {
      "min": "0xbd555555555555546",
      "max": "0xbfffffffffffffff0",
      "status": "1MVDYgVaSN6iKKEsbzRUAYFrYJadLYZvvZ"
    },
    {
      "min": "0xbfffffffffffffff0",
      "max": "0xc2aaaaaaaaaaaaa9a",
      "status": "1MVDYgVaSN6iKKEsbzRUAYFrYJadLYZvvZ"
    },
    {
      "min": "0xc2aaaaaaaaaaaaa9a",
      "max": "0xc5555555555555544",
      "status": "1MVDYgVaSN6iKKEsbzRUAYFrYJadLYZvvZ"
    },
    {
      "min": "0xc5555555555555544",
      "max": "0xc7fffffffffffffee",
      "status": "1MVDYgVaSN6iKKEsbzRUAYFrYJadLYZvvZ"
    },
    {
      "min": "0xc7fffffffffffffee",
      "max": "0xcaaaaaaaaaaaaaa98",
      "status": "1MVDYgVaSN6iKKEsbzRUAYFrYJadLYZvvZ"
    },
    {
      "min": "0xcaaaaaaaaaaaaaa98",
      "max": "0xcd555555555555542",
      "status": "1MVDYgVaSN6iKKEsbzRUAYFrYJadLYZvvZ"
    },
    {
      "min": "0xcd555555555555542",
      "max": "0xcffffffffffffffec",
      "status": "1MVDYgVaSN6iKKEsbzRUAYFrYJadLYZvvZ"
    },
    {
      "min": "0xcffffffffffffffec",
      "max": "0xd2aaaaaaaaaaaaa96",
      "status": "1MVDYgVaSN6iKKEsbzRUAYFrYJadLYZvvZ"
    },
    {
      "min": "0xd2aaaaaaaaaaaaa96",
      "max": "0xd5555555555555540",
      "status": "1MVDYgVaSN6iKKEsbzRUAYFrYJadLYZvvZ"
    },
    {
      "min": "0xd5555555555555540",
      "max": "0xd7fffffffffffffea",
      "status": "1MVDYgVaSN6iKKEsbzRUAYFrYJadLYZvvZ"
    },
    {
      "min": "0xd7fffffffffffffea",
      "max": "0xdaaaaaaaaaaaaaa94",
      "status": "1MVDYgVaSN6iKKEsbzRUAYFrYJadLYZvvZ"
    },
    {
      "min": "0xdaaaaaaaaaaaaaa94",
      "max": "0xdd55555555555553e",
      "status": "1MVDYgVaSN6iKKEsbzRUAYFrYJadLYZvvZ"
    },
    {
      "min": "0xdd55555555555553e",
      "max": "0xdffffffffffffffe8",
      "status": "1MVDYgVaSN6iKKEsbzRUAYFrYJadLYZvvZ"
    },
    {
      "min": "0xdffffffffffffffe8",
      "max": "0xe2aaaaaaaaaaaaa92",
      "status": "1MVDYgVaSN6iKKEsbzRUAYFrYJadLYZvvZ"
    },
    {
      "min": "0xe2aaaaaaaaaaaaa92",
      "max": "0xe555555555555553c",
      "status": "1MVDYgVaSN6iKKEsbzRUAYFrYJadLYZvvZ"
    },
    {
      "min": "0xe555555555555553c",
      "max": "0xe7fffffffffffffe6",
      "status": "1MVDYgVaSN6iKKEsbzRUAYFrYJadLYZvvZ"
    },
    {
      "min": "0xe7fffffffffffffe6",
      "max": "0xeaaaaaaaaaaaaaa90",
      "status": "1MVDYgVaSN6iKKEsbzRUAYFrYJadLYZvvZ"
    },
    {
      "min": "0xeaaaaaaaaaaaaaa90",
      "max": "0xed55555555555553a",
      "status": "1MVDYgVaSN6iKKEsbzRUAYFrYJadLYZvvZ"
    },
    {
      "min": "0xed55555555555553a",
      "max": "0xeffffffffffffffe4",
      "status": "1MVDYgVaSN6iKKEsbzRUAYFrYJadLYZvvZ"
    },
    {
      "min": "0xeffffffffffffffe4",
      "max": "0xf2aaaaaaaaaaaaa8e",
      "status": "1MVDYgVaSN6iKKEsbzRUAYFrYJadLYZvvZ"
    },
    {
      "min": "0xf2aaaaaaaaaaaaa8e",
      "max": "0xf5555555555555538",
      "status": "1MVDYgVaSN6iKKEsbzRUAYFrYJadLYZvvZ"
    },
    {
      "min": "0xf5555555555555538",
      "max": "0xf7fffffffffffffe2",
      "status": "1MVDYgVaSN6iKKEsbzRUAYFrYJadLYZvvZ"
    },
    {
      "min": "0xf7fffffffffffffe2",
      "max": "0xfaaaaaaaaaaaaaa8c",
      "status": "1MVDYgVaSN6iKKEsbzRUAYFrYJadLYZvvZ"
    },
    {
      "min": "0xfaaaaaaaaaaaaaa8c",
      "max": "0xfd555555555555536",
      "status": "1MVDYgVaSN6iKKEsbzRUAYFrYJadLYZvvZ"
    },
    {
      "min": "0xfd555555555555536",
      "max": "0xfffffffffffffffff",
      "status": "1MVDYgVaSN6iKKEsbzRUAYFrYJadLYZvvZ"
    }
  ]
}
